aimanager/__init__.py
aimanager/cli.py
aimanager/version.py
aimanager-0.1.1.dist-info/LICENSE
aimanager-0.1.1.dist-info/METADATA
aimanager-0.1.1.dist-info/WHEEL
aimanager-0.1.1.dist-info/entry_points.txt
aimanager-0.1.1.dist-info/top_level.txt
aimanager-0.1.1.dist-info/RECORD
