Metadata-Version: 2.1
Name: aimanager
Version: 0.1.1
Author: Ayoub Assis
Author-email: assis.ayoub@gmail.com
Requires-Python: >=3.8
License-File: LICENSE
Requires-Dist: lgg
